skopein/__init__.py
skopein/jpg.py
skopein/png.py
skopein-0.2.0.dist-info/licenses/LICENSE
skopein-0.2.0.dist-info/METADATA
skopein-0.2.0.dist-info/WHEEL
skopein-0.2.0.dist-info/top_level.txt
skopein-0.2.0.dist-info/RECORD
