Metadata-Version: 2.4
Name: skopein
Version: 0.2.0
Summary: tools for digital ballistics analysis of image files
Author: Bruno Constanzo
Author-email: bconstanzo@ufasta.edu.ar
License: LGPL 2.1
Project-URL: Source, https://github.com/bconstanzo/skopein/
Classifier: Development Status :: 3 - Alpha
Classifier: Intended Audience :: Developers
Classifier: License :: OSI Approved :: GNU Lesser General Public License v2 or later (LGPLv2+)
Classifier: Programming Language :: Python :: 3.10
Requires-Python: >=3.10
License-File: LICENSE
Dynamic: author
Dynamic: author-email
Dynamic: classifier
Dynamic: description
Dynamic: description-content-type
Dynamic: license
Dynamic: license-file
Dynamic: project-url
Dynamic: requires-python
Dynamic: summary
